README.md
setup.cfg
setup.py
RKF/__init__.py
RKF/rkf.py
RKF.egg-info/PKG-INFO
RKF.egg-info/SOURCES.txt
RKF.egg-info/dependency_links.txt
RKF.egg-info/requires.txt
RKF.egg-info/top_level.txt