Metadata-Version: 2.1
Name: RKF
Version: 1.0.6
Summary: Implementation of Runge-Kutta Fehlberg method to numerically solve system of ODEs.
Home-page: https://github.com/amirh0ss3in/RKF
Author: Amirhossein Rezaei
Author-email: amirh.rezaei@mail.sbu.ac.ir
License: MIT
Download-URL: https://github.com/amirh0ss3in/RKF/archive/V_1.0.6.tar.gz
Keywords: RKF,ODE,Runge-Kutta,Runge-Kutta Fehlberg
Platform: UNKNOWN
Classifier: Development Status :: 5 - Production/Stable
Classifier: Topic :: Scientific/Engineering
Classifier: License :: OSI Approved :: MIT License
Classifier: Programming Language :: Python :: 3
Classifier: Programming Language :: Python :: 3.4
Classifier: Programming Language :: Python :: 3.5
Classifier: Programming Language :: Python :: 3.6
Classifier: Programming Language :: Python :: 3.7
Classifier: Programming Language :: Python :: 3.8
Classifier: Programming Language :: Python :: 3.9
